{
  "CI": [
    "Wirtschaftswissenschaften",
    "Fachzeitschriften"
  ],
  "CME": [
    "Wirtschaftswissenschaften",
    "Fachzeitschriften"
  ],
  "CGMW": [
    "Wirtschaftswissenschaften",
    "Fachzeitschriften"
  ],
  "BURE": [
    "Wirtschaftswissenschaften",
    "Fachzeitschriften"
  ],
  "BUBH": [
    "Wirtschaftswissenschaften",
    "Fachzeitschriften"
  ],
  "BTME": [
    "Wirtschaftswissenschaften",
    "Fachzeitschriften"
  ],
  "BME": [
    "Wirtschaftswissenschaften",
    "Fachzeitschriften"
  ],
  "BGWP": [
    "Wirtschaftswissenschaften",
    "Fachzeitschriften"
  ],
  "BAA": [
    "Wirtschaftswissenschaften",
    "Fachzeitschriften"
  ],
  "ARAB": [
    "Wirtschaftswissenschaften",
    "Fachzeitschriften"
  ],
  "AMW": [
    "Wirtschaftswissenschaften",
    "Technik",
    "Fachzeitschriften"
  ],
  "AMP": [
    "Wirtschaftswissenschaften",
    "Fachzeitschriften"
  ],
  "AKA": [
    "Wirtschaftswissenschaften",
    "Fachzeitschriften"
  ],
  "AGRI": [
    "Wirtschaftswissenschaften",
    "Fachzeitschriften"
  ],
  "VD": [
    "Technik",
    "Wirtschaftswissenschaften",
    "Fachzeitschriften"
  ],
  "SPI": [
    "Technik",
    "Fachzeitschriften"
  ],
  "SCMW": [
    "Technik",
    "Fachzeitschriften"
  ],
  "PHAP": [
    "Technik",
    "Fachzeitschriften"
  ],
  "PC": [
    "Technik",
    "Fachzeitschriften"
  ],
  "OGR": [
    "Technik",
    "Wirtschaftswissenschaften",
    "Fachzeitschriften"
  ],
  "MUTE": [
    "Technik",
    "Fachzeitschriften"
  ],
  "MABL": [
    "Technik",
    "Fachzeitschriften"
  ],
  "LB": [
    "Technik",
    "Fachzeitschriften"
  ],
  "KSM": [
    "Recht",
    "Fachzeitschriften"
  ],
  "JRW": [
    "Technik",
    "Wirtschaftswissenschaften",
    "Fachzeitschriften"
  ],
  "IGMW": [
    "Technik",
    "Fachzeitschriften"
  ],
  "ICT": [
    "Technik",
    "Fachzeitschriften"
  ],
  "HTH": [
    "Technik",
    "Fachzeitschriften"
  ],
  "HREC": [
    "Technik",
    "Fachzeitschriften"
  ],
  "HBUS": [
    "Technik",
    "Fachzeitschriften"
  ],
  "GAGI": [
    "Technik",
    "Fachzeitschriften"
  ],
  "FK": [
    "Technik",
    "Fachzeitschriften"
  ],
  "ERIP": [
    "Technik",
    "Fachzeitschriften"
  ],
  "EPPE": [
    "Technik",
    "Fachzeitschriften"
  ],
  "ENRE": [
    "Technik",
    "Fachzeitschriften"
  ],
  "EMW": [
    "Technik",
    "Fachzeitschriften"
  ],
  "EIRB": [
    "Technik",
    "Fachzeitschriften"
  ],
  "EI": [
    "Technik",
    "Fachzeitschriften"
  ],
  "DQW": [
    "Technik",
    "Wirtschaftswissenschaften",
    "Fachzeitschriften"
  ],
  "DQ": [
    "Technik",
    "Wirtschaftswissenschaften",
    "Fachzeitschriften"
  ],
  "DEBA": [
    "Technik",
    "Fachzeitschriften"
  ],
  "DATA": [
    "Technik",
    "Wirtschaftswissenschaften",
    "Fachzeitschriften"
  ],
  "CMW": [
    "Technik",
    "Fachzeitschriften"
  ],
  "CDM": [
    "Technik",
    "Fachzeitschriften"
  ],
  "CAVE": [
    "Technik",
    "Fachzeitschriften"
  ],
  "BRSC": [
    "Technik",
    "Fachzeitschriften"
  ],
  "BIWI": [
    "Technik",
    "Fachzeitschriften"
  ],
  "AUPR": [
    "Technik",
    "Fachzeitschriften"
  ],
  "AUKO": [
    "Technik",
    "Fachzeitschriften"
  ],
  "LAW": [
    "Recht",
    "Fachzeitschriften"
  ],
  "FUS": [
    "Recht",
    "Wirtschaftswissenschaften",
    "Fachzeitschriften"
  ],
  "EAWO": [
    "Recht",
    "Wirtschaftswissenschaften",
    "Fachzeitschriften"
  ],
  "PJP": [
    "Psychologie",
    "Fachzeitschriften"
  ],
  "PJPR": [
    "Psychologie",
    "Fachzeitschriften"
  ],
  "PJCP": [
    "Psychologie",
    "Fachzeitschriften"
  ],
  "JNC": [
    "Psychologie",
    "Fachzeitschriften"
  ],
  "JBS": [
    "Psychologie",
    "Sozialwissenschaften",
    "Fachzeitschriften"
  ],
  "IJAR": [
    "Fachzeitschriften",
    "Sozialwissenschaften"
  ],
  "ZAAA": [
    "Wirtschaftswissenschaften",
    "Fachzeitschriften",
    "Psychologie",
    "Sozialwissenschaften"
  ],
  "POPS": [
    "Fachzeitschriften",
    "Psychologie",
    "Sozialwissenschaften"
  ],
  "WLB": [
    "Wirtschaftswissenschaften",
    "Fachzeitschriften",
    "Technik"
  ],
  "TAWI": [
    "Wirtschaftswissenschaften",
    "Fachzeitschriften"
  ],
  "DZI": [
    "Sozialwissenschaften"
  ],
  "BIKE": [
    "Wirtschaftswissenschaften",
    "Fachzeitschriften"
  ],
  "BWI": [
    "Wirtschaftswissenschaften",
    "Fachzeitschriften"
  ],
  "NDV": [
    "Fachzeitschriften",
    "Recht",
    "Sozialwissenschaften"
  ],
  "TAI": [
    "Wirtschaftswissenschaften",
    "Fachzeitschriften"
  ],
  "HANA": [
    "Fachzeitschriften"
  ],
  "HAND": [
    "Wirtschaftswissenschaften",
    "Fachzeitschriften"
  ],
  "GG": [
    "Wirtschaftswissenschaften",
    "Fachzeitschriften"
  ],
  "WRP": [
    "Wirtschaftswissenschaften",
    "Fachzeitschriften",
    "Recht"
  ],
  "FJSB": [
    "Fachzeitschriften",
    "Sozialwissenschaften"
  ],
  "DLGM": [
    "Wirtschaftswissenschaften",
    "Fachzeitschriften"
  ],
  "GI": [
    "Wirtschaftswissenschaften",
    "Fachzeitschriften"
  ],
  "FIM": [
    "Wirtschaftswissenschaften",
    "Fachzeitschriften"
  ],
  "MAR": [
    "Wirtschaftswissenschaften",
    "Fachzeitschriften"
  ],
  "WUW": [
    "Wirtschaftswissenschaften",
    "Fachzeitschriften"
  ],
  "WUV": [
    "Wirtschaftswissenschaften",
    "Fachzeitschriften"
  ],
  "LAK": [
    "Wirtschaftswissenschaften",
    "Fachzeitschriften",
    "Recht"
  ],
  "NPE": [
    "Fachzeitschriften",
    "Psychologie"
  ],
  "ASSC": [
    "Wirtschaftswissenschaften",
    "Fachzeitschriften"
  ],
  "WUB": [
    "Wirtschaftswissenschaften",
    "Fachzeitschriften",
    "Recht"
  ],
  "MAC": [
    "Fachzeitschriften"
  ],
  "PACK": [
    "Wirtschaftswissenschaften",
    "Fachzeitschriften"
  ],
  "GITL": [
    "Fachzeitschriften",
    "Technik"
  ],
  "PCW": [
    "Fachzeitschriften"
  ],
  "AUON": [
    "Wirtschaftswissenschaften",
    "Fachzeitschriften"
  ],
  "DTZ": [
    "Wirtschaftswissenschaften",
    "Fachzeitschriften"
  ],
  "PCH": [
    "Fachzeitschriften",
    "Psychologie"
  ],
  "GITS": [
    "Fachzeitschriften"
  ],
  "AHOR": [
    "Fachzeitschriften"
  ],
  "SBAN": [
    "Wirtschaftswissenschaften",
    "Fachzeitschriften"
  ],
  "KOCA": [
    "Wirtschaftswissenschaften",
    "Fachzeitschriften"
  ],
  "THEX": [
    "Wirtschaftswissenschaften",
    "Fachzeitschriften"
  ],
  "SOBE": [
    "Fachzeitschriften",
    "Psychologie",
    "Sozialwissenschaften"
  ],
  "FLWA": [
    "Fachzeitschriften"
  ],
  "FLWI": [
    "Wirtschaftswissenschaften",
    "Fachzeitschriften"
  ],
  "WUWE": [
    "Wirtschaftswissenschaften",
    "Fachzeitschriften",
    "Recht"
  ],
  "JEEM": [
    "Wirtschaftswissenschaften",
    "Fachzeitschriften"
  ],
  "ZM": [
    "Wirtschaftswissenschaften",
    "Fachzeitschriften"
  ],
  "DSZ": [
    "Wirtschaftswissenschaften",
    "Fachzeitschriften"
  ],
  "SOLI": [
    "LIT",
    "Sozialwissenschaften"
  ],
  "TRE": [
    "Wirtschaftswissenschaften",
    "Fachzeitschriften"
  ],
  "DST": [
    "Wirtschaftswissenschaften"
  ],
  "STBG": [
    "Wirtschaftswissenschaften",
    "Fachzeitschriften",
    "Recht"
  ],
  "VDIA": [
    "Fachzeitschriften"
  ],
  "ZVS": [
    "Wirtschaftswissenschaften",
    "Fachzeitschriften",
    "Psychologie"
  ],
  "VDIN": [
    "Wirtschaftswissenschaften",
    "Fachzeitschriften",
    "Technik"
  ],
  "DSB": [
    "Fachzeitschriften",
    "Recht",
    "Technik"
  ],
  "WTRE": [
    "Fachzeitschriften",
    "Sozialwissenschaften"
  ],
  "MF": [
    "Wirtschaftswissenschaften",
    "Fachzeitschriften",
    "Technik"
  ],
  "DBWV": [
    "Wirtschaftswissenschaften",
    "Fachzeitschriften",
    "Recht"
  ],
  "VCNE": [
    "Wirtschaftswissenschaften",
    "Fachzeitschriften"
  ],
  "MM": [
    "Wirtschaftswissenschaften",
    "Fachzeitschriften"
  ],
  "MT": [
    "Wirtschaftswissenschaften",
    "Fachzeitschriften",
    "Technik"
  ],
  "IFOL": [
    "Wirtschaftswissenschaften"
  ],
  "FS": [
    "Wirtschaftswissenschaften",
    "Fachzeitschriften"
  ],
  "AFZ": [
    "Wirtschaftswissenschaften",
    "Fachzeitschriften"
  ],
  "WEBE": [
    "Wirtschaftswissenschaften",
    "Fachzeitschriften",
    "Technik"
  ],
  "CIOD": [
    "Fachzeitschriften"
  ],
  "WEBR": [
    "Fachzeitschriften"
  ],
  "FB": [
    "Wirtschaftswissenschaften",
    "Fachzeitschriften"
  ],
  "FH": [
    "Wirtschaftswissenschaften",
    "Fachzeitschriften",
    "Technik"
  ],
  "ZNER": [
    "Wirtschaftswissenschaften",
    "Fachzeitschriften",
    "Recht"
  ],
  "FM": [
    "Wirtschaftswissenschaften",
    "Fachzeitschriften"
  ],
  "SMA": [
    "Wirtschaftswissenschaften",
    "Fachzeitschriften"
  ],
  "MDA": [
    "Fachzeitschriften",
    "Sozialwissenschaften"
  ],
  "PHAM": [
    "Wirtschaftswissenschaften",
    "Fachzeitschriften"
  ],
  "BONL": [
    "Fachzeitschriften"
  ],
  "MDR": [
    "Fachzeitschriften",
    "Recht"
  ],
  "BOND": [
    "Wirtschaftswissenschaften",
    "Fachzeitschriften"
  ],
  "AUA": [
    "Wirtschaftswissenschaften",
    "Fachzeitschriften",
    "Recht"
  ],
  "AUB": [
    "Wirtschaftswissenschaften",
    "Fachzeitschriften"
  ],
  "DFI": [
    "Wirtschaftswissenschaften",
    "Fachzeitschriften"
  ],
  "VEC": [
    "Wirtschaftswissenschaften",
    "Fachzeitschriften"
  ],
  "AUW": [
    "Wirtschaftswissenschaften",
    "Fachzeitschriften"
  ],
  "REFA": [
    "Wirtschaftswissenschaften",
    "Fachzeitschriften"
  ],
  "VRAG": [
    "Wirtschaftswissenschaften",
    "Fachzeitschriften"
  ],
  "LMZ": [
    "Wirtschaftswissenschaften",
    "Fachzeitschriften"
  ],
  "RLH": [
    "Wirtschaftswissenschaften",
    "Fachzeitschriften"
  ],
  "MARC": [
    "Wirtschaftswissenschaften",
    "Fachzeitschriften"
  ],
  "PUA": [
    "Wirtschaftswissenschaften",
    "Fachzeitschriften",
    "Psychologie"
  ],
  "IMWI": [
    "Wirtschaftswissenschaften",
    "Fachzeitschriften",
    "Recht"
  ],
  "SB": [
    "Wirtschaftswissenschaften",
    "Fachzeitschriften"
  ],
  "ERP": [
    "Wirtschaftswissenschaften",
    "Fachzeitschriften",
    "Technik"
  ],
  "OMNI": [
    "Wirtschaftswissenschaften",
    "Fachzeitschriften"
  ],
  "BBLO": [
    "Wirtschaftswissenschaften",
    "Fachzeitschriften"
  ],
  "CAV": [
    "Fachzeitschriften",
    "Technik"
  ],
  "IBF": [
    "Wirtschaftswissenschaften",
    "Fachzeitschriften"
  ],
  "ANKR": [
    "Fachzeitschriften",
    "Sozialwissenschaften"
  ],
  "FERT": [
    "Fachzeitschriften",
    "Technik"
  ],
  "ABAU": [
    "Wirtschaftswissenschaften",
    "Fachzeitschriften"
  ],
  "KOR": [
    "Wirtschaftswissenschaften",
    "Fachzeitschriften",
    "Recht"
  ],
  "CAD": [
    "Fachzeitschriften",
    "Technik"
  ],
  "SOFI": [
    "Wirtschaftswissenschaften",
    "Sozialwissenschaften"
  ],
  "SOFO": [
    "Fachzeitschriften",
    "Sozialwissenschaften"
  ],
  "LI": [
    "Wirtschaftswissenschaften",
    "Fachzeitschriften",
    "Technik"
  ],
  "HIF": [
    "Wirtschaftswissenschaften",
    "Fachzeitschriften"
  ],
  "ONR": [
    "Wirtschaftswissenschaften",
    "Fachzeitschriften"
  ],
  "PROJ": [
    "Wirtschaftswissenschaften",
    "Fachzeitschriften"
  ],
  "STB": [
    "Wirtschaftswissenschaften",
    "Fachzeitschriften",
    "Recht"
  ],
  "ZRP": [
    "Fachzeitschriften",
    "Recht"
  ],
  "IWPR": [
    "Wirtschaftswissenschaften"
  ],
  "SOC": [
    "Fachzeitschriften",
    "Psychologie",
    "Sozialwissenschaften"
  ],
  "EUIB": [
    "Fachzeitschriften"
  ],
  "UNTE": [
    "Wirtschaftswissenschaften",
    "Fachzeitschriften"
  ],
  "STS": [
    "Wirtschaftswissenschaften",
    "Fachzeitschriften"
  ],
  "ABZ": [
    "Wirtschaftswissenschaften",
    "Fachzeitschriften"
  ],
  "MREV": [
    "Wirtschaftswissenschaften",
    "Fachzeitschriften"
  ],
  "PMGI": [
    "Fachzeitschriften"
  ],
  "BANK": [
    "Wirtschaftswissenschaften",
    "Fachzeitschriften"
  ],
  "CFO": [
    "Wirtschaftswissenschaften",
    "Fachzeitschriften"
  ],
  "QJIA": [
    "Wirtschaftswissenschaften",
    "Fachzeitschriften"
  ],
  "MAKR": [
    "Wirtschaftswissenschaften",
    "Fachzeitschriften"
  ],
  "TAXI": [
    "Wirtschaftswissenschaften",
    "Fachzeitschriften"
  ],
  "NEUL": [
    "Fachzeitschriften"
  ],
  "DKT": [
    "Fachzeitschriften",
    "Technik"
  ],
  "GA": [
    "Wirtschaftswissenschaften",
    "Fachzeitschriften"
  ],
  "GHR": [
    "Fachzeitschriften",
    "Recht"
  ],
  "JFAV": [
    "Wirtschaftswissenschaften",
    "Fachzeitschriften"
  ],
  "ECON": [
    "LIT",
    "Wirtschaftswissenschaften"
  ],
  "KMAG": [
    "Wirtschaftswissenschaften",
    "Fachzeitschriften"
  ],
  "MID": [
    "Wirtschaftswissenschaften",
    "Fachzeitschriften"
  ],
  "WEFO": [
    "Fachzeitschriften",
    "Technik"
  ],
  "TRUC": [
    "Wirtschaftswissenschaften",
    "Fachzeitschriften",
    "Technik"
  ],
  "SBIL": [
    "Fachzeitschriften"
  ],
  "JOR": [
    "Fachzeitschriften",
    "Recht"
  ],
  "AOB": [
    "Fachzeitschriften",
    "Recht"
  ],
  "FOGR": [
    "Technik"
  ],
  "PRIN": [
    "Technik"
  ],
  "AWCH": [
    "Wirtschaftswissenschaften",
    "Fachzeitschriften"
  ],
  "RAU": [
    "Fachzeitschriften",
    "Psychologie"
  ],
  "WIME": [
    "Wirtschaftswissenschaften",
    "Fachzeitschriften",
    "Psychologie",
    "Recht"
  ],
  "OEWI": [
    "Wirtschaftswissenschaften",
    "Fachzeitschriften"
  ],
  "LP": [
    "Wirtschaftswissenschaften",
    "Fachzeitschriften"
  ],
  "HBNI": [
    "Wirtschaftswissenschaften",
    "Fachzeitschriften"
  ],
  "ZFGK": [
    "Wirtschaftswissenschaften",
    "Fachzeitschriften",
    "Recht"
  ],
  "CHX": [
    "Wirtschaftswissenschaften",
    "Fachzeitschriften"
  ],
  "BUIM": [
    "Wirtschaftswissenschaften",
    "Fachzeitschriften"
  ],
  "ZFGG": [
    "Wirtschaftswissenschaften",
    "Fachzeitschriften"
  ],
  "DBM": [
    "Wirtschaftswissenschaften",
    "Fachzeitschriften"
  ],
  "DBL": [
    "Wirtschaftswissenschaften",
    "Fachzeitschriften"
  ],
  "MAV": [
    "Wirtschaftswissenschaften",
    "Fachzeitschriften",
    "Technik"
  ],
  "HORS": [
    "Wirtschaftswissenschaften",
    "Fachzeitschriften"
  ],
  "VIM": [
    "Wirtschaftswissenschaften",
    "Fachzeitschriften"
  ],
  "KUK": [
    "Wirtschaftswissenschaften",
    "Fachzeitschriften"
  ],
  "DBW": [
    "Wirtschaftswissenschaften",
    "Fachzeitschriften"
  ],
  "PSYT": [
    "Psychologie"
  ],
  "GMST": [
    "Wirtschaftswissenschaften",
    "Fachzeitschriften",
    "Recht"
  ],
  "EXFO": [
    "Wirtschaftswissenschaften",
    "Fachzeitschriften"
  ],
  "ABES": [
    "Wirtschaftswissenschaften",
    "Fachzeitschriften"
  ],
  "DINM": [
    "Fachzeitschriften",
    "Technik"
  ],
  "BAMA": [
    "Wirtschaftswissenschaften",
    "Fachzeitschriften"
  ],
  "ZWF": [
    "Wirtschaftswissenschaften",
    "Fachzeitschriften"
  ],
  "CLIN": [
    "Wirtschaftswissenschaften",
    "Fachzeitschriften"
  ],
  "PSYA": [
    "Fachzeitschriften",
    "Psychologie"
  ],
  "STAA": [
    "Fachzeitschriften",
    "Recht",
    "Sozialwissenschaften"
  ],
  "WFP": [
    "Wirtschaftswissenschaften",
    "Fachzeitschriften",
    "Technik"
  ],
  "GAST": [
    "Wirtschaftswissenschaften",
    "Fachzeitschriften"
  ],
  "NGZ": [
    "Wirtschaftswissenschaften",
    "Fachzeitschriften"
  ],
  "CAIT": [
    "Fachzeitschriften",
    "Technik"
  ],
  "PKV": [
    "Fachzeitschriften",
    "Psychologie"
  ],
  "SBRE": [
    "Wirtschaftswissenschaften",
    "Fachzeitschriften"
  ],
  "FLOW": [
    "Wirtschaftswissenschaften",
    "Fachzeitschriften"
  ],
  "RTH": [
    "Fachzeitschriften",
    "Recht",
    "Sozialwissenschaften"
  ],
  "RTJ": [
    "Wirtschaftswissenschaften",
    "Fachzeitschriften",
    "Technik"
  ],
  "IP": [
    "Fachzeitschriften",
    "Sozialwissenschaften"
  ],
  "HMD": [
    "Wirtschaftswissenschaften",
    "Fachzeitschriften",
    "Technik"
  ],
  "EDBW": [
    "Wirtschaftswissenschaften",
    "Fachzeitschriften"
  ],
  "ZKF": [
    "Wirtschaftswissenschaften",
    "Fachzeitschriften"
  ],
  "EM": [
    "Fachzeitschriften",
    "Technik"
  ],
  "ED": [
    "Wirtschaftswissenschaften",
    "Fachzeitschriften"
  ],
  "EA": [
    "Fachzeitschriften",
    "Technik"
  ],
  "EB": [
    "Wirtschaftswissenschaften",
    "Fachzeitschriften",
    "Recht"
  ],
  "RAAK": [
    "Wirtschaftswissenschaften",
    "Fachzeitschriften"
  ],
  "SHF": [
    "Wirtschaftswissenschaften",
    "Fachzeitschriften",
    "Technik"
  ],
  "DLT": [
    "Fachzeitschriften",
    "Technik"
  ],
  "AFP": [
    "Wirtschaftswissenschaften",
    "Fachzeitschriften",
    "Recht"
  ],
  "BEFO": [
    "LIT",
    "Wirtschaftswissenschaften"
  ],
  "AMIF": [
    "Fachzeitschriften"
  ],
  "SSP": [
    "Wirtschaftswissenschaften",
    "Fachzeitschriften",
    "Technik"
  ],
  "CIPA": [
    "Wirtschaftswissenschaften",
    "Fachzeitschriften"
  ],
  "USTB": [
    "Wirtschaftswissenschaften",
    "Fachzeitschriften"
  ],
  "OGEM": [
    "Wirtschaftswissenschaften",
    "Fachzeitschriften"
  ],
  "IM": [
    "Wirtschaftswissenschaften",
    "Fachzeitschriften"
  ],
  "PROD": [
    "Fachzeitschriften",
    "Technik"
  ],
  "PROC": [
    "Fachzeitschriften",
    "Technik"
  ],
  "HORA": [
    "Wirtschaftswissenschaften",
    "Fachzeitschriften"
  ],
  "ISR": [
    "Wirtschaftswissenschaften",
    "Fachzeitschriften",
    "Technik"
  ],
  "PMGC": [
    "Fachzeitschriften"
  ],
  "CHAN": [
    "Fachzeitschriften"
  ],
  "IA": [
    "Wirtschaftswissenschaften",
    "Fachzeitschriften",
    "Technik"
  ],
  "ISI": [
    "Fachzeitschriften",
    "Sozialwissenschaften"
  ],
  "VJH": [
    "Wirtschaftswissenschaften",
    "Fachzeitschriften",
    "Sozialwissenschaften"
  ],
  "EJOP": [
    "Fachzeitschriften",
    "Psychologie"
  ],
  "MUM": [
    "Wirtschaftswissenschaften",
    "Fachzeitschriften"
  ],
  "JBM": [
    "Wirtschaftswissenschaften",
    "Fachzeitschriften"
  ],
  "EUSO": [
    "Wirtschaftswissenschaften",
    "Fachzeitschriften"
  ],
  "ASP": [
    "Wirtschaftswissenschaften",
    "Fachzeitschriften",
    "Technik"
  ],
  "ASW": [
    "Wirtschaftswissenschaften",
    "Fachzeitschriften"
  ],
  "MCKW": [
    "Wirtschaftswissenschaften",
    "Fachzeitschriften"
  ],
  "PAFO": [
    "Wirtschaftswissenschaften",
    "Fachzeitschriften"
  ],
  "TETE": [
    "Fachzeitschriften",
    "Technik"
  ],
  "IMC": [
    "Wirtschaftswissenschaften",
    "Fachzeitschriften",
    "Technik"
  ],
  "BBL": [
    "Wirtschaftswissenschaften",
    "Fachzeitschriften"
  ],
  "OEKZ": [
    "Wirtschaftswissenschaften",
    "Fachzeitschriften"
  ],
  "BUMT": [
    "Wirtschaftswissenschaften",
    "Fachzeitschriften",
    "Recht"
  ],
  "BBA": [
    "Wirtschaftswissenschaften",
    "Fachzeitschriften"
  ],
  "IMP": [
    "Fachzeitschriften"
  ],
  "OEKO": [
    "Wirtschaftswissenschaften",
    "Fachzeitschriften"
  ],
  "CARD": [
    "Wirtschaftswissenschaften",
    "Fachzeitschriften",
    "Recht"
  ],
  "INFO": [
    "Technik"
  ],
  "BVPE": [
    "Wirtschaftswissenschaften",
    "Fachzeitschriften",
    "Psychologie"
  ],
  "KEM": [
    "Fachzeitschriften",
    "Technik"
  ],
  "HVM": [
    "Wirtschaftswissenschaften",
    "Fachzeitschriften"
  ],
  "SPAO": [
    "Wirtschaftswissenschaften",
    "Fachzeitschriften"
  ],
  "KE": [
    "Fachzeitschriften",
    "Technik"
  ],
  "ITG": [
    "Wirtschaftswissenschaften",
    "Fachzeitschriften",
    "Technik"
  ],
  "BVPN": [
    "Wirtschaftswissenschaften",
    "Fachzeitschriften",
    "Psychologie"
  ],
  "KH": [
    "Wirtschaftswissenschaften",
    "Fachzeitschriften"
  ],
  "ITB": [
    "Wirtschaftswissenschaften",
    "Fachzeitschriften",
    "Technik"
  ],
  "KM": [
    "Fachzeitschriften",
    "Technik"
  ],
  "AATG": [
    "Wirtschaftswissenschaften",
    "Fachzeitschriften"
  ],
  "KU": [
    "Wirtschaftswissenschaften",
    "Fachzeitschriften"
  ],
  "SPAR": [
    "Wirtschaftswissenschaften",
    "Fachzeitschriften"
  ],
  "ITT": [
    "Wirtschaftswissenschaften",
    "Fachzeitschriften"
  ],
  "KEP": [
    "Wirtschaftswissenschaften",
    "Fachzeitschriften"
  ],
  "AAA": [
    "Wirtschaftswissenschaften",
    "Fachzeitschriften"
  ],
  "ZSR": [
    "Fachzeitschriften",
    "Sozialwissenschaften"
  ],
  "SINV": [
    "Wirtschaftswissenschaften",
    "Fachzeitschriften"
  ],
  "DD": [
    "Wirtschaftswissenschaften",
    "Fachzeitschriften"
  ],
  "AUBI": [
    "Fachzeitschriften",
    "Technik"
  ],
  "KRES": [
    "Wirtschaftswissenschaften",
    "Fachzeitschriften"
  ],
  "EUFI": [
    "Wirtschaftswissenschaften",
    "Fachzeitschriften"
  ],
  "ABIL": [
    "Wirtschaftswissenschaften",
    "Fachzeitschriften"
  ],
  "SWW": [
    "Fachzeitschriften",
    "Technik"
  ],
  "BIM": [
    "Wirtschaftswissenschaften",
    "Fachzeitschriften"
  ],
  "ERBS": [
    "Wirtschaftswissenschaften",
    "Fachzeitschriften",
    "Recht"
  ],
  "AECO": [
    "Wirtschaftswissenschaften",
    "Fachzeitschriften"
  ],
  "UNED": [
    "Wirtschaftswissenschaften",
    "Fachzeitschriften"
  ],
  "JFNS": [
    "Wirtschaftswissenschaften",
    "Fachzeitschriften"
  ],
  "VERW": [
    "Wirtschaftswissenschaften",
    "Fachzeitschriften",
    "Recht"
  ],
  "RBS": [
    "Wirtschaftswissenschaften",
    "Fachzeitschriften"
  ],
  "CWT": [
    "Fachzeitschriften",
    "Technik"
  ],
  "VERK": [
    "Wirtschaftswissenschaften",
    "Fachzeitschriften"
  ],
  "GOV": [
    "Fachzeitschriften",
    "Technik"
  ],
  "GOP": [
    "Wirtschaftswissenschaften",
    "Fachzeitschriften"
  ],
  "LGK": [
    "Wirtschaftswissenschaften",
    "Fachzeitschriften",
    "Technik"
  ],
  "IMMO": [
    "Wirtschaftswissenschaften",
    "Fachzeitschriften"
  ],
  "IMMA": [
    "Wirtschaftswissenschaften",
    "Fachzeitschriften"
  ],
  "QZ": [
    "Wirtschaftswissenschaften",
    "Fachzeitschriften",
    "Technik"
  ],
  "WJ": [
    "Wirtschaftswissenschaften",
    "Fachzeitschriften"
  ],
  "QE": [
    "Wirtschaftswissenschaften",
    "Fachzeitschriften",
    "Technik"
  ],
  "IHSL": [
    "Wirtschaftswissenschaften",
    "Sozialwissenschaften"
  ],
  "ZFS": [
    "Fachzeitschriften",
    "Psychologie",
    "Sozialwissenschaften"
  ],
  "ZFR": [
    "Fachzeitschriften",
    "Recht",
    "Sozialwissenschaften"
  ],
  "WM": [
    "Wirtschaftswissenschaften",
    "Fachzeitschriften",
    "Recht"
  ],
  "ZFP": [
    "Wirtschaftswissenschaften",
    "Fachzeitschriften",
    "Psychologie"
  ],
  "GJHR": [
    "Wirtschaftswissenschaften",
    "Fachzeitschriften",
    "Psychologie"
  ],
  "COWI": [
    "Wirtschaftswissenschaften",
    "Fachzeitschriften"
  ],
  "ZFT": [
    "Wirtschaftswissenschaften",
    "Fachzeitschriften",
    "Sozialwissenschaften"
  ],
  "WW": [
    "Wirtschaftswissenschaften",
    "Fachzeitschriften"
  ],
  "ZFO": [
    "Wirtschaftswissenschaften",
    "Fachzeitschriften",
    "Psychologie"
  ],
  "BUHA": [
    "Fachzeitschriften"
  ],
  "WP": [
    "Wirtschaftswissenschaften",
    "Fachzeitschriften",
    "Psychologie"
  ],
  "DTRS": [
    "Wirtschaftswissenschaften",
    "Fachzeitschriften"
  ],
  "GFKM": [
    "Wirtschaftswissenschaften",
    "Fachzeitschriften"
  ],
  "IWB": [
    "Wirtschaftswissenschaften",
    "Fachzeitschriften",
    "Technik"
  ],
  "BUSR": [
    "Wirtschaftswissenschaften",
    "Fachzeitschriften"
  ],
  "HSR": [
    "Fachzeitschriften",
    "Sozialwissenschaften"
  ],
  "IWT": [
    "Wirtschaftswissenschaften",
    "Fachzeitschriften"
  ],
  "JUKA": [
    "Wirtschaftswissenschaften",
    "Fachzeitschriften"
  ],
  "RISK": [
    "Wirtschaftswissenschaften",
    "Fachzeitschriften"
  ],
  "IAA": [
    "Wirtschaftswissenschaften",
    "Fachzeitschriften",
    "Sozialwissenschaften"
  ],
  "WEN": [
    "Fachzeitschriften"
  ],
  "IAC": [
    "Wirtschaftswissenschaften",
    "Fachzeitschriften",
    "Sozialwissenschaften"
  ],
  "PASS": [
    "Wirtschaftswissenschaften",
    "Fachzeitschriften"
  ],
  "FVW": [
    "Wirtschaftswissenschaften",
    "Fachzeitschriften"
  ],
  "VALU": [
    "Wirtschaftswissenschaften",
    "Fachzeitschriften"
  ],
  "AAS": [
    "Wirtschaftswissenschaften",
    "Fachzeitschriften"
  ],
  "CEAB": [
    "Technik"
  ],
  "DVZB": [
    "Wirtschaftswissenschaften",
    "Fachzeitschriften"
  ],
  "ETEC": [
    "Fachzeitschriften",
    "Technik"
  ],
  "AEQ": [
    "Wirtschaftswissenschaften",
    "Fachzeitschriften"
  ],
  "SVER": [
    "Wirtschaftswissenschaften",
    "Fachzeitschriften"
  ],
  "PORT": [
    "Wirtschaftswissenschaften",
    "Fachzeitschriften"
  ],
  "ZOE": [
    "Wirtschaftswissenschaften",
    "Fachzeitschriften",
    "Psychologie"
  ],
  "PP": [
    "Wirtschaftswissenschaften",
    "Fachzeitschriften",
    "Technik"
  ],
  "GEW": [
    "Wirtschaftswissenschaften",
    "Fachzeitschriften"
  ],
  "HMDS": [
    "Wirtschaftswissenschaften",
    "Fachzeitschriften",
    "Technik"
  ],
  "GET": [
    "Wirtschaftswissenschaften",
    "Fachzeitschriften"
  ],
  "STIF": [
    "Wirtschaftswissenschaften",
    "Fachzeitschriften"
  ],
  "BUS": [
    "Wirtschaftswissenschaften",
    "Fachzeitschriften"
  ],
  "BUW": [
    "Wirtschaftswissenschaften",
    "Fachzeitschriften"
  ],
  "PF": [
    "Wirtschaftswissenschaften",
    "Fachzeitschriften"
  ],
  "BUM": [
    "Wirtschaftswissenschaften",
    "Fachzeitschriften"
  ],
  "MALE": [
    "Wirtschaftswissenschaften",
    "Fachzeitschriften"
  ],
  "ABMS": [
    "Fachzeitschriften"
  ],
  "PM": [
    "Wirtschaftswissenschaften",
    "Fachzeitschriften"
  ],
  "UMPS": [
    "Fachzeitschriften",
    "Psychologie"
  ],
  "DDS": [
    "Wirtschaftswissenschaften",
    "Fachzeitschriften"
  ],
  "ZFAA": [
    "Wirtschaftswissenschaften",
    "Fachzeitschriften",
    "Sozialwissenschaften"
  ],
  "DDH": [
    "Wirtschaftswissenschaften",
    "Fachzeitschriften"
  ],
  "FSEA": [
    "Fachzeitschriften"
  ],
  "WPSY": [
    "Wirtschaftswissenschaften",
    "Fachzeitschriften",
    "Psychologie"
  ],
  "EXTR": [
    "Wirtschaftswissenschaften",
    "Fachzeitschriften"
  ],
  "ORDO": [
    "Wirtschaftswissenschaften",
    "Fachzeitschriften"
  ],
  "WWT": [
    "Fachzeitschriften",
    "Technik"
  ],
  "KAFU": [
    "Wirtschaftswissenschaften",
    "Fachzeitschriften"
  ],
  "LMZA": [
    "Fachzeitschriften"
  ],
  "AUIN": [
    "Wirtschaftswissenschaften",
    "Fachzeitschriften",
    "Technik"
  ],
  "ANT": [
    "Fachzeitschriften",
    "Technik"
  ],
  "ANP": [
    "Fachzeitschriften"
  ],
  "PSS": [
    "Fachzeitschriften",
    "Psychologie"
  ],
  "KURS": [
    "Wirtschaftswissenschaften",
    "Fachzeitschriften"
  ],
  "BSPI": [
    "Wirtschaftswissenschaften",
    "Fachzeitschriften"
  ],
  "FSA": [
    "Fachzeitschriften"
  ],
  "EMAR": [
    "Wirtschaftswissenschaften",
    "Fachzeitschriften"
  ],
  "FSE": [
    "Wirtschaftswissenschaften",
    "Fachzeitschriften"
  ],
  "BULK": [
    "Fachzeitschriften",
    "Technik"
  ],
  "STGU": [
    "Wirtschaftswissenschaften",
    "Fachzeitschriften"
  ],
  "GWW": [
    "Wirtschaftswissenschaften",
    "Fachzeitschriften"
  ],
  "GWP": [
    "Wirtschaftswissenschaften",
    "Fachzeitschriften"
  ],
  "DVZ": [
    "Wirtschaftswissenschaften",
    "Fachzeitschriften"
  ],
  "OELA": [
    "Wirtschaftswissenschaften",
    "Fachzeitschriften"
  ],
  "DVP": [
    "Wirtschaftswissenschaften",
    "Fachzeitschriften"
  ],
  "FLUI": [
    "Fachzeitschriften",
    "Technik"
  ],
  "VRR": [
    "Wirtschaftswissenschaften",
    "Fachzeitschriften",
    "Recht"
  ],
  "THBE": [
    "Wirtschaftswissenschaften",
    "Fachzeitschriften"
  ],
  "JCSM": [
    "Wirtschaftswissenschaften",
    "Fachzeitschriften"
  ],
  "CASH": [
    "Wirtschaftswissenschaften",
    "Fachzeitschriften"
  ],
  "VRA": [
    "Wirtschaftswissenschaften",
    "Fachzeitschriften",
    "Recht"
  ],
  "WAO": [
    "LIT",
    "Sozialwissenschaften"
  ],
  "CO": [
    "Wirtschaftswissenschaften",
    "Fachzeitschriften",
    "Recht"
  ],
  "WWGR": [
    "Wirtschaftswissenschaften",
    "Fachzeitschriften"
  ],
  "ADIW": [
    "Wirtschaftswissenschaften",
    "Fachzeitschriften"
  ],
  "CF": [
    "Wirtschaftswissenschaften",
    "Fachzeitschriften",
    "Recht"
  ],
  "LEMO": [
    "Fachzeitschriften"
  ],
  "CZ": [
    "Fachzeitschriften",
    "Technik"
  ],
  "MUAR": [
    "Wirtschaftswissenschaften",
    "Fachzeitschriften"
  ],
  "WAX": [
    "Fachzeitschriften",
    "Sozialwissenschaften"
  ],
  "CS": [
    "Wirtschaftswissenschaften",
    "Fachzeitschriften"
  ],
  "CP": [
    "Wirtschaftswissenschaften",
    "Fachzeitschriften",
    "Technik"
  ],
  "CW": [
    "Wirtschaftswissenschaften",
    "Fachzeitschriften",
    "Technik"
  ],
  "CT": [
    "Wirtschaftswissenschaften",
    "Fachzeitschriften",
    "Technik"
  ],
  "BILA": [
    "Wirtschaftswissenschaften",
    "Fachzeitschriften"
  ],
  "BILN": [
    "Wirtschaftswissenschaften",
    "Fachzeitschriften"
  ],
  "AVFB": [
    "Fachzeitschriften"
  ],
  "GELD": [
    "Wirtschaftswissenschaften",
    "Fachzeitschriften"
  ],
  "PLM": [
    "Wirtschaftswissenschaften",
    "Fachzeitschriften"
  ],
  "ENEV": [
    "Fachzeitschriften",
    "Technik"
  ],
  "DIM": [
    "Wirtschaftswissenschaften",
    "Fachzeitschriften"
  ],
  "LOG": [
    "Wirtschaftswissenschaften",
    "Fachzeitschriften",
    "Technik"
  ],
  "IFOK": [
    "Wirtschaftswissenschaften"
  ],
  "IFOD": [
    "Wirtschaftswissenschaften",
    "Fachzeitschriften"
  ],
  "PDKK": [
    "Fachzeitschriften"
  ],
  "HDLG": [
    "Fachzeitschriften",
    "Technik"
  ],
  "XPSY": [
    "Psychologie"
  ],
  "INSP": [
    "Fachzeitschriften",
    "Technik"
  ],
  "INST": [
    "Fachzeitschriften",
    "Technik"
  ],
  "IHKK": [
    "Wirtschaftswissenschaften",
    "Fachzeitschriften"
  ],
  "IFOS": [
    "Wirtschaftswissenschaften",
    "Fachzeitschriften"
  ],
  "CBIL": [
    "Fachzeitschriften",
    "Technik"
  ],
  "DIBA": [
    "Wirtschaftswissenschaften",
    "Fachzeitschriften"
  ],
  "CBS": [
    "Fachzeitschriften"
  ],
  "OWG": [
    "Wirtschaftswissenschaften",
    "Fachzeitschriften",
    "Sozialwissenschaften"
  ],
  "PPS": [
    "Wirtschaftswissenschaften",
    "Fachzeitschriften"
  ],
  "GEPR": [
    "Wirtschaftswissenschaften",
    "Fachzeitschriften"
  ],
  "LEDI": [
    "Wirtschaftswissenschaften",
    "Fachzeitschriften"
  ],
  "ZFWP": [
    "Wirtschaftswissenschaften",
    "Fachzeitschriften"
  ],
  "ZFWU": [
    "Wirtschaftswissenschaften",
    "Fachzeitschriften",
    "Sozialwissenschaften"
  ],
  "IX": [
    "Fachzeitschriften",
    "Technik"
  ],
  "AUTO": [
    "Wirtschaftswissenschaften",
    "Fachzeitschriften",
    "Technik"
  ],
  "IS": [
    "Wirtschaftswissenschaften",
    "Fachzeitschriften"
  ],
  "VM": [
    "Fachzeitschriften",
    "Recht"
  ],
  "AUTH": [
    "Wirtschaftswissenschaften",
    "Fachzeitschriften"
  ],
  "AUTI": [
    "Fachzeitschriften",
    "Technik"
  ],
  "VR": [
    "Wirtschaftswissenschaften",
    "Fachzeitschriften"
  ],
  "VT": [
    "Fachzeitschriften",
    "Technik"
  ],
  "VV": [
    "Wirtschaftswissenschaften",
    "Fachzeitschriften"
  ],
  "VW": [
    "Wirtschaftswissenschaften",
    "Fachzeitschriften"
  ],
  "KONP": [
    "Fachzeitschriften",
    "Technik"
  ],
  "MTA": [
    "Fachzeitschriften",
    "Technik"
  ],
  "KONT": [
    "Wirtschaftswissenschaften",
    "Fachzeitschriften"
  ],
  "METE": [
    "Fachzeitschriften"
  ],
  "EPRA": [
    "Fachzeitschriften",
    "Technik"
  ],
  "TW": [
    "Wirtschaftswissenschaften",
    "Fachzeitschriften"
  ],
  "HOLZ": [
    "Technik"
  ],
  "MCDB": [
    "Wirtschaftswissenschaften",
    "Fachzeitschriften",
    "Recht"
  ],
  "PWI": [
    "Wirtschaftswissenschaften",
    "Fachzeitschriften",
    "Recht"
  ],
  "BE": [
    "Wirtschaftswissenschaften",
    "Fachzeitschriften"
  ],
  "BA": [
    "Wirtschaftswissenschaften",
    "Fachzeitschriften"
  ],
  "BB": [
    "Wirtschaftswissenschaften",
    "Fachzeitschriften",
    "Recht"
  ],
  "BM": [
    "Wirtschaftswissenschaften",
    "Fachzeitschriften",
    "Technik"
  ],
  "BI": [
    "Wirtschaftswissenschaften",
    "Fachzeitschriften"
  ],
  "EPP": [
    "Fachzeitschriften",
    "Technik"
  ],
  "BLIS": [
    "LIT",
    "Wirtschaftswissenschaften",
    "Sozialwissenschaften"
  ],
  "BW": [
    "Wirtschaftswissenschaften",
    "Fachzeitschriften"
  ],
  "FIWI": [
    "Wirtschaftswissenschaften",
    "Fachzeitschriften"
  ],
  "KOEL": [
    "Wirtschaftswissenschaften"
  ],
  "GRER": [
    "Wirtschaftswissenschaften",
    "Fachzeitschriften"
  ],
  "MFZB": [
    "Fachzeitschriften",
    "Sozialwissenschaften"
  ],
  "EJCO": [
    "Fachzeitschriften",
    "Psychologie"
  ],
  "LMZS": [
    "Wirtschaftswissenschaften",
    "Fachzeitschriften"
  ],
  "PMEM": [
    "Fachzeitschriften"
  ],
  "MTME": [
    "Wirtschaftswissenschaften",
    "Fachzeitschriften",
    "Technik"
  ],
  "IJPR": [
    "Fachzeitschriften",
    "Psychologie"
  ],
  "FAMR": [
    "Fachzeitschriften",
    "Recht"
  ],
  "LOGI": [
    "Wirtschaftswissenschaften",
    "Fachzeitschriften",
    "Technik"
  ],
  "VUV": [
    "Fachzeitschriften",
    "Psychologie"
  ],
  "BFUP": [
    "Wirtschaftswissenschaften",
    "Fachzeitschriften"
  ],
  "AKTS": [
    "Wirtschaftswissenschaften",
    "Fachzeitschriften",
    "Recht"
  ],
  "PUGK": [
    "Fachzeitschriften",
    "Psychologie",
    "Sozialwissenschaften"
  ],
  "OP": [
    "Fachzeitschriften",
    "Technik"
  ],
  "IFKP": [
    "Fachzeitschriften"
  ],
  "HWWA": [
    "Wirtschaftswissenschaften"
  ],
  "LKH": [
    "Wirtschaftswissenschaften",
    "Fachzeitschriften"
  ],
  "KFZB": [
    "Wirtschaftswissenschaften",
    "Fachzeitschriften"
  ],
  "ZFBF": [
    "Wirtschaftswissenschaften",
    "Fachzeitschriften"
  ],
  "VERS": [
    "Wirtschaftswissenschaften",
    "Fachzeitschriften"
  ],
  "FLW": [
    "Wirtschaftswissenschaften",
    "Fachzeitschriften"
  ],
  "DEI": [
    "Wirtschaftswissenschaften",
    "Fachzeitschriften"
  ],
  "EEK": [
    "Wirtschaftswissenschaften",
    "Fachzeitschriften",
    "Technik"
  ],
  "SMF": [
    "Wirtschaftswissenschaften",
    "Fachzeitschriften"
  ],
  "DIWW": [
    "Wirtschaftswissenschaften",
    "Fachzeitschriften"
  ],
  "DIWR": [
    "Fachzeitschriften",
    "Sozialwissenschaften"
  ],
  "FLF": [
    "Wirtschaftswissenschaften",
    "Fachzeitschriften"
  ],
  "KUSI": [
    "Fachzeitschriften",
    "Technik"
  ],
  "CMAG": [
    "Fachzeitschriften",
    "Technik"
  ],
  "PUUM": [
    "Wirtschaftswissenschaften",
    "Fachzeitschriften",
    "Sozialwissenschaften"
  ],
  "KUSE": [
    "Recht"
  ],
  "EUZW": [
    "Wirtschaftswissenschaften",
    "Fachzeitschriften",
    "Recht"
  ],
  "ZFKO": [
    "Wirtschaftswissenschaften",
    "Fachzeitschriften"
  ],
  "ABAL": [
    "Fachzeitschriften"
  ],
  "ZFKE": [
    "Wirtschaftswissenschaften",
    "Fachzeitschriften"
  ],
  "KUST": [
    "Fachzeitschriften",
    "Technik"
  ],
  "EWK": [
    "Fachzeitschriften",
    "Psychologie",
    "Sozialwissenschaften"
  ],
  "DSTZ": [
    "Wirtschaftswissenschaften",
    "Fachzeitschriften",
    "Recht"
  ],
  "SCOP": [
    "Wirtschaftswissenschaften",
    "Fachzeitschriften",
    "Technik"
  ],
  "LABO": [
    "Fachzeitschriften",
    "Technik"
  ],
  "CAPI": [
    "Fachzeitschriften"
  ],
  "OEIM": [
    "Wirtschaftswissenschaften",
    "Fachzeitschriften"
  ],
  "KONS": [
    "Wirtschaftswissenschaften",
    "Fachzeitschriften"
  ],
  "GEBM": [
    "Wirtschaftswissenschaften",
    "Fachzeitschriften"
  ],
  "VOB": [
    "Wirtschaftswissenschaften",
    "Fachzeitschriften",
    "Recht",
    "Technik"
  ],
  "FBIE": [
    "Wirtschaftswissenschaften",
    "Fachzeitschriften"
  ],
  "AHGZ": [
    "Wirtschaftswissenschaften",
    "Fachzeitschriften"
  ],
  "UR": [
    "Wirtschaftswissenschaften",
    "Fachzeitschriften",
    "Recht"
  ],
  "HTT": [
    "Wirtschaftswissenschaften",
    "Fachzeitschriften"
  ],
  "AHGA": [
    "Fachzeitschriften"
  ],
  "FPP": [
    "Fachzeitschriften",
    "Psychologie"
  ],
  "SUG": [
    "Fachzeitschriften",
    "Sozialwissenschaften"
  ],
  "ESTE": [
    "Technik"
  ],
  "ESTB": [
    "Wirtschaftswissenschaften",
    "Fachzeitschriften",
    "Recht"
  ],
  "SOSY": [
    "Fachzeitschriften",
    "Sozialwissenschaften"
  ],
  "ABKL": [
    "Fachzeitschriften"
  ],
  "ACQ": [
    "Wirtschaftswissenschaften",
    "Fachzeitschriften"
  ],
  "ACAS": [
    "Wirtschaftswissenschaften",
    "Fachzeitschriften"
  ],
  "ZUG": [
    "Wirtschaftswissenschaften",
    "Fachzeitschriften"
  ],
  "BLEC": [
    "Fachzeitschriften",
    "Technik"
  ],
  "AWOE": [
    "Wirtschaftswissenschaften",
    "Fachzeitschriften"
  ],
  "SOSI": [
    "Fachzeitschriften",
    "Sozialwissenschaften"
  ],
  "CYBI": [
    "Wirtschaftswissenschaften",
    "Fachzeitschriften"
  ],
  "TEC": [
    "Fachzeitschriften"
  ],
  "AUEL": [
    "Fachzeitschriften",
    "Technik"
  ],
  "JSPP": [
    "Fachzeitschriften",
    "Psychologie"
  ],
  "GFGH": [
    "Wirtschaftswissenschaften",
    "Fachzeitschriften"
  ],
  "PMJ": [
    "Wirtschaftswissenschaften",
    "Fachzeitschriften"
  ],
  "FINR": [
    "Wirtschaftswissenschaften",
    "Fachzeitschriften",
    "Recht"
  ],
  "REND": [
    "Wirtschaftswissenschaften",
    "Fachzeitschriften"
  ],
  "ABSC": [
    "Fachzeitschriften"
  ],
  "MIND": [
    "Wirtschaftswissenschaften"
  ],
  "DNK": [
    "Wirtschaftswissenschaften",
    "Fachzeitschriften"
  ],
  "QUAL": [
    "Wirtschaftswissenschaften",
    "Fachzeitschriften"
  ],
  "NEEN": [
    "Fachzeitschriften",
    "Technik"
  ],
  "SJB": [
    "Wirtschaftswissenschaften",
    "Fachzeitschriften",
    "Sozialwissenschaften"
  ],
  "RCUA": [
    "Wirtschaftswissenschaften",
    "Fachzeitschriften"
  ],
  "IT": [
    "Fachzeitschriften",
    "Technik"
  ],
  "ZPMP": [
    "Fachzeitschriften"
  ],
  "WIM": [
    "Wirtschaftswissenschaften",
    "Fachzeitschriften"
  ],
  "LAPR": [
    "Fachzeitschriften",
    "Technik"
  ],
  "MAMI": [
    "Wirtschaftswissenschaften",
    "Fachzeitschriften"
  ],
  "VUNM": [
    "Wirtschaftswissenschaften",
    "Fachzeitschriften"
  ],
  "WIR": [
    "Wirtschaftswissenschaften",
    "Fachzeitschriften"
  ],
  "MAMA": [
    "Wirtschaftswissenschaften",
    "Fachzeitschriften",
    "Technik"
  ],
  "GDI": [
    "Wirtschaftswissenschaften",
    "Fachzeitschriften"
  ],
  "TWA": [
    "Fachzeitschriften"
  ],
  "DIST": [
    "Wirtschaftswissenschaften",
    "Fachzeitschriften"
  ],
  "CID": [
    "Fachzeitschriften",
    "Technik"
  ],
  "PSYC": [
    "Fachzeitschriften",
    "Psychologie"
  ],
  "MSR": [
    "Fachzeitschriften",
    "Technik"
  ],
  "GVPA": [
    "Fachzeitschriften"
  ],
  "FEMS": [
    "Fachzeitschriften",
    "Sozialwissenschaften"
  ],
  "TWP": [
    "Wirtschaftswissenschaften",
    "Fachzeitschriften",
    "Psychologie"
  ],
  "JBWW": [
    "Wirtschaftswissenschaften",
    "Fachzeitschriften"
  ],
  "GVPR": [
    "Wirtschaftswissenschaften",
    "Fachzeitschriften"
  ],
  "DAE": [
    "Wirtschaftswissenschaften",
    "Fachzeitschriften"
  ],
  "CFLA": [
    "Wirtschaftswissenschaften",
    "Fachzeitschriften",
    "Recht"
  ],
  "THPH": [
    "Fachzeitschriften",
    "Technik"
  ],
  "WIRO": [
    "Wirtschaftswissenschaften",
    "Fachzeitschriften",
    "Recht"
  ],
  "TT": [
    "Wirtschaftswissenschaften",
    "Fachzeitschriften",
    "Technik"
  ],
  "TR": [
    "Fachzeitschriften",
    "Technik"
  ],
  "HDJ": [
    "Wirtschaftswissenschaften",
    "Fachzeitschriften"
  ],
  "TJ": [
    "Wirtschaftswissenschaften",
    "Fachzeitschriften"
  ],
  "KFZW": [
    "Wirtschaftswissenschaften",
    "Fachzeitschriften"
  ],
  "DAR": [
    "Wirtschaftswissenschaften",
    "Fachzeitschriften",
    "Recht"
  ],
  "CITL": [
    "Fachzeitschriften",
    "Technik"
  ],
  "REGA": [
    "Wirtschaftswissenschaften",
    "Fachzeitschriften"
  ],
  "MIET": [
    "Fachzeitschriften",
    "Recht"
  ],
  "AWPA": [
    "Fachzeitschriften",
    "Psychologie",
    "Sozialwissenschaften"
  ],
  "HOE": [
    "Wirtschaftswissenschaften",
    "Fachzeitschriften"
  ],
  "AE": [
    "Fachzeitschriften",
    "Technik"
  ],
  "DWW": [
    "Wirtschaftswissenschaften",
    "Fachzeitschriften"
  ],
  "AF": [
    "Wirtschaftswissenschaften",
    "Fachzeitschriften"
  ],
  "AEZT": [
    "Wirtschaftswissenschaften",
    "Fachzeitschriften"
  ],
  "ADCO": [
    "Wirtschaftswissenschaften",
    "Fachzeitschriften"
  ],
  "NOTB": [
    "Fachzeitschriften",
    "Recht"
  ],
  "AO": [
    "Wirtschaftswissenschaften",
    "Fachzeitschriften"
  ],
  "GLIP": [
    "Wirtschaftswissenschaften",
    "Fachzeitschriften",
    "Technik"
  ],
  "HOR": [
    "Wirtschaftswissenschaften",
    "Fachzeitschriften"
  ],
  "AT": [
    "Fachzeitschriften",
    "Technik"
  ],
  "VST": [
    "Wirtschaftswissenschaften",
    "Fachzeitschriften"
  ],
  "BRAU": [
    "Wirtschaftswissenschaften",
    "Fachzeitschriften"
  ],
  "CATI": [
    "Wirtschaftswissenschaften",
    "Fachzeitschriften"
  ],
  "PEMA": [
    "Wirtschaftswissenschaften",
    "Fachzeitschriften"
  ],
  "INDB": [
    "Wirtschaftswissenschaften",
    "Fachzeitschriften",
    "Sozialwissenschaften"
  ],
  "DI": [
    "Wirtschaftswissenschaften",
    "Sozialwissenschaften",
    "Fachzeitschriften"
  ],
  "DMS": [
    "Wirtschaftswissenschaften",
    "Fachzeitschriften"
  ],
  "EAW": [
    "Wirtschaftswissenschaften",
    "Fachzeitschriften"
  ],
  "EMRE": [
    "Wirtschaftswissenschaften",
    "Fachzeitschriften"
  ],
  "EU": [
    "Wirtschaftswissenschaften",
    "Fachzeitschriften"
  ],
  "EVIN": [
    "Wirtschaftswissenschaften",
    "Fachzeitschriften"
  ],
  "FIME": [
    "Wirtschaftswissenschaften",
    "Fachzeitschriften"
  ],
  "FSM": [
    "Wirtschaftswissenschaften",
    "Fachzeitschriften"
  ],
  "GDP": [
    "Wirtschaftswissenschaften",
    "Fachzeitschriften"
  ],
  "GUBU": [
    "Wirtschaftswissenschaften",
    "Fachzeitschriften"
  ],
  "GUIN": [
    "Wirtschaftswissenschaften",
    "Fachzeitschriften"
  ],
  "HILA": [
    "Wirtschaftswissenschaften",
    "Sozialwissenschaften",
    "Fachzeitschriften"
  ],
  "HLOG": [
    "Wirtschaftswissenschaften",
    "Fachzeitschriften"
  ],
  "IFAM": [
    "Wirtschaftswissenschaften",
    "Fachzeitschriften"
  ],
  "IFMW": [
    "Wirtschaftswissenschaften",
    "Fachzeitschriften"
  ],
  "INJO": [
    "Wirtschaftswissenschaften",
    "Fachzeitschriften"
  ],
  "ISBF": [
    "Wirtschaftswissenschaften",
    "Fachzeitschriften"
  ],
  "JEF": [
    "Wirtschaftswissenschaften",
    "Fachzeitschriften"
  ],
  "JPV": [
    "Wirtschaftswissenschaften",
    "Sozialwissenschaften",
    "Fachzeitschriften"
  ],
  "LHMW": [
    "Wirtschaftswissenschaften",
    "Fachzeitschriften"
  ],
  "MBP": [
    "Wirtschaftswissenschaften",
    "Fachzeitschriften"
  ],
  "MBW": [
    "Wirtschaftswissenschaften",
    "Fachzeitschriften"
  ],
  "MEMW": [
    "Wirtschaftswissenschaften",
    "Fachzeitschriften"
  ],
  "OER": [
    "Wirtschaftswissenschaften",
    "Fachzeitschriften"
  ],
  "PHM": [
    "Wirtschaftswissenschaften",
    "Fachzeitschriften"
  ],
  "PJIM": [
    "Wirtschaftswissenschaften",
    "Fachzeitschriften"
  ],
  "PJLS": [
    "Wirtschaftswissenschaften",
    "Sozialwissenschaften",
    "Fachzeitschriften"
  ],
  "PSJ": [
    "Wirtschaftswissenschaften",
    "Fachzeitschriften"
  ],
  "PVD": [
    "Wirtschaftswissenschaften",
    "Fachzeitschriften"
  ],
  "REGI": [
    "Wirtschaftswissenschaften",
    "Fachzeitschriften"
  ],
  "REMW": [
    "Wirtschaftswissenschaften",
    "Fachzeitschriften"
  ],
  "SAFR": [
    "Wirtschaftswissenschaften",
    "Fachzeitschriften"
  ],
  "SBP": [
    "Wirtschaftswissenschaften",
    "Fachzeitschriften"
  ],
  "SLO": [
    "Wirtschaftswissenschaften",
    "Fachzeitschriften"
  ],
  "TMW": [
    "Wirtschaftswissenschaften",
    "Fachzeitschriften"
  ],
  "UTIL": [
    "Wirtschaftswissenschaften",
    "Fachzeitschriften"
  ],
  "WSIR": [
    "Wirtschaftswissenschaften",
    "Fachzeitschriften"
  ],
  "WWON": [
    "Wirtschaftswissenschaften",
    "Fachzeitschriften"
  ],
  "DISK": [
    "Fachzeitschriften",
    "Sozialwissenschaften"
  ],
  "JGSI": [
    "Fachzeitschriften",
    "Sozialwissenschaften"
  ],
  "NEHO": [
    "Fachzeitschriften",
    "Sozialwissenschaften"
  ],
  "PAPE": [
    "Fachzeitschriften",
    "Sozialwissenschaften"
  ],
  "PJSS": [
    "Fachzeitschriften",
    "Sozialwissenschaften"
  ],
  "POPE": [
    "Fachzeitschriften",
    "Sozialwissenschaften"
  ],
  "TDIA": [
    "Fachzeitschriften",
    "Sozialwissenschaften"
  ],
  "ZFF": [
    "Fachzeitschriften",
    "Sozialwissenschaften"
  ],
  "KTX": [
    "Fachzeitschriften",
    "Psychologie"
  ],
  "MAON": [
    "Technik"
  ],
  "HTEC": [
    "Technik"
  ],
  "TWNE": [
    "Wirtschaftswissenschaften"
  ],
  "GUG": [
    "Sozialwissenschaften",
    "Fachzeitschriften"
  ],
  "ELEO": [
    "Technik"
  ],
  "AKS": [
    "Sozialwissenschaften",
    "Fachzeitschriften"
  ],
  "ASPA": [
    "Sozialwissenschaften",
    "Fachzeitschriften"
  ],
  "JER": [
    "Sozialwissenschaften",
    "Fachzeitschriften"
  ],
  "PGE": [
    "Wirtschaftswissenschaften"
  ],
  "FINE": [
    "Wirtschaftswissenschaften"
  ],
  "MUB": [
    "Wirtschaftswissenschaften"
  ],
  "FMAI": [
    "Wirtschaftswissenschaften",
    "Fachzeitschriften"
  ],
  "TUD": [
    "Sozialwissenschaften",
    "Fachzeitschriften"
  ],
  "KUCH": [
    "Wirtschaftswissenschaften"
  ],
  "FOWE": [
    "Technik"
  ],
  "ENER": [
    "Wirtschaftswissenschaften"
  ],
  "TIAM": [
    "Wirtschaftswissenschaften",
    "Fachzeitschriften"
  ],
  "SOA": [
    "Sozialwissenschaften",
    "Fachzeitschriften"
  ],
  "KONZ": [
    "Wirtschaftswissenschaften",
    "Fachzeitschriften"
  ],
  "AUMO": [
    "Technik"
  ],
  "KUSO": [
    "Sozialwissenschaften",
    "Fachzeitschriften"
  ],
  "HPRW": [
    "Technik"
  ],
  "JOBS": [
    "Wirtschaftswissenschaften",
    "Fachzeitschriften"
  ],
  "JOS": [
    "Wirtschaftswissenschaften",
    "Fachzeitschriften"
  ],
  "PERI": [
    "Sozialwissenschaften",
    "Fachzeitschriften"
  ],
  "SOAS": [
    "Sozialwissenschaften",
    "Fachzeitschriften"
  ]
}
